pynaptan/__init__.py
pynaptan/exceptions.py
pynaptan/naptan.py
pynaptan/nptg.py
pynaptan/py.typed
pynaptan-0.2.0.dist-info/METADATA
pynaptan-0.2.0.dist-info/WHEEL
pynaptan-0.2.0.dist-info/LICENSE
pynaptan-0.2.0.dist-info/RECORD
