Metadata-Version: 2.1
Name: pynaptan
Version: 0.2.0
Summary: Python package for naptan
Home-page: https://github.com/ciaranmccormick/pynaptan
License: MIT
Keywords: NaPTAN,bus stops,stops,open data
Author: Ciaran McCormick
Author-email: ciaranmccormick@gmail.com
Requires-Python: >=3.8,<4.0
Classifier: Development Status :: 3 - Alpha
Classifier: Intended Audience :: Developers
Classifier: License :: OSI Approved :: MIT License
Classifier: Operating System :: OS Independent
Classifier: Programming Language :: Python :: 3
Classifier: Programming Language :: Python :: 3.8
Classifier: Programming Language :: Python :: 3.9
Classifier: Programming Language :: Python :: 3.10
Classifier: Programming Language :: Python :: 3.11
Classifier: Topic :: Software Development :: Libraries :: Python Modules
Requires-Dist: httpx (>=0.23.0,<0.24.0)
Requires-Dist: pydantic (>=1.9.1,<2.0.0)
Requires-Dist: requests (>=2.28.1,<3.0.0)
Project-URL: Repository, https://github.com/ciaranmccormick/pynaptan
